sheetpakage/__init__.py
sheetpakage/sheetops.py
sheetpakage-0.1.0.dist-info/METADATA
sheetpakage-0.1.0.dist-info/WHEEL
sheetpakage-0.1.0.dist-info/top_level.txt
sheetpakage-0.1.0.dist-info/RECORD
